eman2/__init__.py
eman2/bibtex.py
eman2/constants.py
eman2/e2converter.py
eman2/e2ih.py
eman2/eman2_logo.png
eman2/protocols.conf
eman2/convert/__init__.py
eman2/convert/convert.py
eman2/convert/dataimport.py
eman2/protocols/__init__.py
eman2/protocols/protocol_autopick_boxer.py
eman2/protocols/protocol_boxing.py
eman2/protocols/protocol_ctf.py
eman2/protocols/protocol_initialmodel.py
eman2/protocols/protocol_initialmodel_sgd.py
eman2/protocols/protocol_reconstruct.py
eman2/protocols/protocol_refine2d.py
eman2/protocols/protocol_refine2d_bispec.py
eman2/protocols/protocol_refineasy.py
eman2/protocols/protocol_tiltvalidate.py
eman2/tests/__init__.py
eman2/tests/test_protocols_eman.py
eman2/viewers/__init__.py
eman2/viewers/viewers.py
scipion_em_eman2-3.6.1.dist-info/LICENSE
scipion_em_eman2-3.6.1.dist-info/METADATA
scipion_em_eman2-3.6.1.dist-info/WHEEL
scipion_em_eman2-3.6.1.dist-info/entry_points.txt
scipion_em_eman2-3.6.1.dist-info/top_level.txt
scipion_em_eman2-3.6.1.dist-info/RECORD
