Metadata-Version: 2.1
Name: scipion-em-eman2
Version: 3.6.1
Summary: Plugin to use EMAN programs within the Scipion framework
Home-page: https://github.com/scipion-em/scipion-em-eman2
Author: Grigory Sharov
Author-email: sharov.grigory@gmail.com
License: UNKNOWN
Project-URL: Bug Reports, https://github.com/scipion-em/scipion-em-eman2/issues
Project-URL: Source, https://github.com/scipion-em/scipion-em-eman2/
Keywords: scipion electron-microscopy cryo-em structural-biology image-processing scipion-3.0
Platform: UNKNOWN
Classifier: Development Status :: 5 - Production/Stable
Classifier: License :: OSI Approved :: GNU General Public License v3 (GPLv3)
Classifier: Programming Language :: Python :: 3
Requires-Dist: scipion-em
